kegg_pathways_completeness/__init__.py
kegg_pathways_completeness/bin/__init__.py
kegg_pathways_completeness/bin/fetch_modules_data.py
kegg_pathways_completeness/bin/give_completeness.py
kegg_pathways_completeness/bin/make_graphs.py
kegg_pathways_completeness/bin/plot_modules_graphs.py
kegg_pathways_completeness/bin/utils.py
kegg_pathways_completeness/bin/parse_hmmtable/make_hmmer_table_tab_separated.py
kegg_pathways_completeness/bin/parse_hmmtable/parse_hmmer_tab_separated_table.py
kegg_pathways_completeness/pathways_data/__init__.py
kegg_pathways_completeness/pathways_data/all_pathways.txt
kegg_pathways_completeness/pathways_data/all_pathways_class.txt
kegg_pathways_completeness/pathways_data/all_pathways_names.txt
kegg_pathways_completeness/pathways_data/definition_separated.txt
kegg_pathways_completeness/pathways_data/graphs.pkl
kegg_pathways_completeness-1.2.1.dist-info/LICENSE
kegg_pathways_completeness-1.2.1.dist-info/METADATA
kegg_pathways_completeness-1.2.1.dist-info/WHEEL
kegg_pathways_completeness-1.2.1.dist-info/entry_points.txt
kegg_pathways_completeness-1.2.1.dist-info/top_level.txt
kegg_pathways_completeness-1.2.1.dist-info/RECORD
