Metadata-Version: 2.2
Name: kegg-pathways-completeness
Version: 1.2.1
Summary: The tool counts completeness of each KEGG pathway for protein sequences.
Author-email: Ekaterina Sakharova <kates@ebi.ac.uk>
License: Apache Software License 2.0
Keywords: bioinformatics,pipelines,metagenomics,kegg
Classifier: Programming Language :: Python :: 3
Classifier: License :: OSI Approved :: Apache Software License
Classifier: Operating System :: OS Independent
Requires-Python: >=3.10
License-File: LICENSE
Requires-Dist: biopython>=1.83
Requires-Dist: networkx>=3.3
Requires-Dist: graphviz>=0.20.3
Requires-Dist: pydot>=3.0.4
Requires-Dist: tomli>=2.0.1
Provides-Extra: dev
Requires-Dist: pre-commit==3.6.0; extra == "dev"
Requires-Dist: black==24.4.2; extra == "dev"
Provides-Extra: test
Requires-Dist: pytest==8.2.2; extra == "test"
Requires-Dist: pytest-workflow==2.1.0; extra == "test"
Requires-Dist: pytest-md==0.2.0; extra == "test"
